[
    {
      "id": 1,
      "first_name": "Jasper",
      "last_name": "Keavy",
      "email": "jkeavy0@rambler.ru",
      "gender": "Male"
    },
    {
      "id": 2,
      "first_name": "Malachi",
      "last_name": "Dimitriev",
      "email": "mdimitriev1@wunderground.com",
      "gender": "Male"
    },
    {
      "id": 3,
      "first_name": "Aguie",
      "last_name": "Shimman",
      "email": "ashimman2@jimdo.com",
      "gender": "Male"
    },
    {
      "id": 4,
      "first_name": "Ulberto",
      "last_name": "Josland",
      "email": "ujosland3@alexa.com",
      "gender": "Male"
    },
    {
      "id": 5,
      "first_name": "Evaleen",
      "last_name": "Darlow",
      "email": "edarlow4@blogs.com",
      "gender": "Genderqueer"
    },
    {
      "id": 6,
      "first_name": "Hedvige",
      "last_name": "Rusling",
      "email": "hrusling5@shop-pro.jp",
      "gender": "Female"
    },
    {
      "id": 7,
      "first_name": "Rafe",
      "last_name": "Somner",
      "email": "rsomner6@timesonline.co.uk",
      "gender": "Male"
    },
    {
      "id": 8,
      "first_name": "Waldemar",
      "last_name": "Dadge",
      "email": "wdadge7@redcross.org",
      "gender": "Male"
    },
    {
      "id": 9,
      "first_name": "Weider",
      "last_name": "Weond",
      "email": "wweond8@foxnews.com",
      "gender": "Male"
    },
    {
      "id": 10,
      "first_name": "Graig",
      "last_name": "Ferneyhough",
      "email": "gferneyhough9@skyrock.com",
      "gender": "Male"
    },
    {
      "id": 11,
      "first_name": "Claudia",
      "last_name": "Brody",
      "email": "cbrodya@fotki.com",
      "gender": "Female"
    },
    {
      "id": 12,
      "first_name": "Chantalle",
      "last_name": "Helmke",
      "email": "chelmkeb@wufoo.com",
      "gender": "Female"
    },
    {
      "id": 13,
      "first_name": "Odele",
      "last_name": "Siddaley",
      "email": "osiddaleyc@redcross.org",
      "gender": "Female"
    },
    {
      "id": 14,
      "first_name": "Rafaelita",
      "last_name": "Middleditch",
      "email": "rmiddleditchd@mit.edu",
      "gender": "Female"
    },
    {
      "id": 15,
      "first_name": "Alikee",
      "last_name": "Stainsby",
      "email": "astainsbye@bloomberg.com",
      "gender": "Female"
    },
    {
      "id": 16,
      "first_name": "Gery",
      "last_name": "Pridmore",
      "email": "gpridmoref@cnet.com",
      "gender": "Male"
    },
    {
      "id": 17,
      "first_name": "Kelsy",
      "last_name": "Jeandet",
      "email": "kjeandetg@about.me",
      "gender": "Female"
    },
    {
      "id": 18,
      "first_name": "Wesley",
      "last_name": "Bonhan",
      "email": "wbonhanh@slideshare.net",
      "gender": "Male"
    },
    {
      "id": 19,
      "first_name": "Bellina",
      "last_name": "Rudgerd",
      "email": "brudgerdi@smugmug.com",
      "gender": "Female"
    },
    {
      "id": 20,
      "first_name": "Herrick",
      "last_name": "Rountree",
      "email": "hrountreej@skyrock.com",
      "gender": "Male"
    },
    {
      "id": 21,
      "first_name": "Josephina",
      "last_name": "Spraging",
      "email": "jspragingk@topsy.com",
      "gender": "Polygender"
    },
    {
      "id": 22,
      "first_name": "Harris",
      "last_name": "Sandey",
      "email": "hsandeyl@hibu.com",
      "gender": "Male"
    },
    {
      "id": 23,
      "first_name": "Ringo",
      "last_name": "Pesticcio",
      "email": "rpesticciom@aboutads.info",
      "gender": "Male"
    },
    {
      "id": 24,
      "first_name": "Antonetta",
      "last_name": "Orviss",
      "email": "aorvissn@goo.ne.jp",
      "gender": "Female"
    },
    {
      "id": 25,
      "first_name": "Weidar",
      "last_name": "Staker",
      "email": "wstakero@fda.gov",
      "gender": "Male"
    },
    {
      "id": 26,
      "first_name": "Jaquith",
      "last_name": "McDougall",
      "email": "jmcdougallp@comcast.net",
      "gender": "Agender"
    },
    {
      "id": 27,
      "first_name": "Mattie",
      "last_name": "Dellenbrook",
      "email": "mdellenbrookq@dropbox.com",
      "gender": "Female"
    },
    {
      "id": 28,
      "first_name": "Marge",
      "last_name": "Blunden",
      "email": "mblundenr@admin.ch",
      "gender": "Female"
    },
    {
      "id": 29,
      "first_name": "Skelly",
      "last_name": "Dewdeny",
      "email": "sdewdenys@harvard.edu",
      "gender": "Polygender"
    },
    {
      "id": 30,
      "first_name": "Leonid",
      "last_name": "Hanwell",
      "email": "lhanwellt@spiegel.de",
      "gender": "Male"
    },
    {
      "id": 31,
      "first_name": "Fabien",
      "last_name": "Bibb",
      "email": "fbibbu@engadget.com",
      "gender": "Male"
    },
    {
      "id": 32,
      "first_name": "Maddy",
      "last_name": "Labern",
      "email": "mlabernv@infoseek.co.jp",
      "gender": "Female"
    },
    {
      "id": 33,
      "first_name": "Lew",
      "last_name": "Rousel",
      "email": "lrouselw@t.co",
      "gender": "Male"
    },
    {
      "id": 34,
      "first_name": "Sena",
      "last_name": "Zanettini",
      "email": "szanettinix@earthlink.net",
      "gender": "Female"
    },
    {
      "id": 35,
      "first_name": "Arie",
      "last_name": "Ferraresi",
      "email": "aferraresiy@oaic.gov.au",
      "gender": "Male"
    },
    {
      "id": 36,
      "first_name": "Gib",
      "last_name": "Verecker",
      "email": "gvereckerz@dedecms.com",
      "gender": "Male"
    },
    {
      "id": 37,
      "first_name": "Morrie",
      "last_name": "Algeo",
      "email": "malgeo10@yahoo.com",
      "gender": "Polygender"
    },
    {
      "id": 38,
      "first_name": "Svend",
      "last_name": "Orcas",
      "email": "sorcas11@ameblo.jp",
      "gender": "Male"
    },
    {
      "id": 39,
      "first_name": "Marlowe",
      "last_name": "Snawdon",
      "email": "msnawdon12@cbsnews.com",
      "gender": "Male"
    },
    {
      "id": 40,
      "first_name": "Irvine",
      "last_name": "Attenborrow",
      "email": "iattenborrow13@mozilla.com",
      "gender": "Male"
    },
    {
      "id": 41,
      "first_name": "Sterne",
      "last_name": "Culp",
      "email": "sculp14@go.com",
      "gender": "Male"
    },
    {
      "id": 42,
      "first_name": "Kendal",
      "last_name": "Willingale",
      "email": "kwillingale15@howstuffworks.com",
      "gender": "Male"
    },
    {
      "id": 43,
      "first_name": "Farica",
      "last_name": "Flannigan",
      "email": "fflannigan16@ucla.edu",
      "gender": "Female"
    },
    {
      "id": 44,
      "first_name": "Daryl",
      "last_name": "Silliman",
      "email": "dsilliman17@qq.com",
      "gender": "Male"
    },
    {
      "id": 45,
      "first_name": "Delphinia",
      "last_name": "Autie",
      "email": "dautie18@earthlink.net",
      "gender": "Female"
    },
    {
      "id": 46,
      "first_name": "Wanids",
      "last_name": "O'Scollee",
      "email": "woscollee19@dmoz.org",
      "gender": "Female"
    },
    {
      "id": 47,
      "first_name": "Doralyn",
      "last_name": "Trathen",
      "email": "dtrathen1a@tripadvisor.com",
      "gender": "Female"
    },
    {
      "id": 48,
      "first_name": "Sheena",
      "last_name": "Geharke",
      "email": "sgeharke1b@moonfruit.com",
      "gender": "Female"
    },
    {
      "id": 49,
      "first_name": "Davita",
      "last_name": "Maclaine",
      "email": "dmaclaine1c@pbs.org",
      "gender": "Female"
    },
    {
      "id": 50,
      "first_name": "Arliene",
      "last_name": "Thing",
      "email": "athing1d@unblog.fr",
      "gender": "Female"
    }
  ]
  